stream_archive_subtitle/__init__.py
stream_archive_subtitle/stream_archive_subtitle.py
stream_archive_subtitle-1.0.8.dist-info/LICENSE
stream_archive_subtitle-1.0.8.dist-info/METADATA
stream_archive_subtitle-1.0.8.dist-info/WHEEL
stream_archive_subtitle-1.0.8.dist-info/entry_points.txt
stream_archive_subtitle-1.0.8.dist-info/top_level.txt
stream_archive_subtitle-1.0.8.dist-info/RECORD
