Metadata-Version: 2.1
Name: stream-archive-subtitle
Version: 1.0.8
Summary: UNKNOWN
Home-page: UNKNOWN
Author: Michael Nolan
Author-email: celegans25@gmail.com
License: UNKNOWN
Platform: UNKNOWN
License-File: LICENSE
Requires-Dist: srt
